devlaunch/__init__.py
devlaunch/completion.py
devlaunch/completion_loader.py
devlaunch/dl.py
devlaunch/completions/__init__.py
devlaunch/completions/dl.bash
devlaunch-0.0.6.dist-info/METADATA
devlaunch-0.0.6.dist-info/WHEEL
devlaunch-0.0.6.dist-info/entry_points.txt
devlaunch-0.0.6.dist-info/licenses/LICENSE
devlaunch-0.0.6.dist-info/RECORD
