Metadata-Version: 2.4
Name: devlaunch
Version: 0.0.6
Summary: DevLaunch - A streamlined CLI for devpod workspaces
Project-URL: Source, https://github.com/blooop/devlaunch
Project-URL: Home, https://github.com/blooop/devlaunch
Author-email: Austin Gregg-Smith <blooop@gmail.com>
License-Expression: MIT
License-File: LICENSE
Requires-Dist: iterfzf>=1.0.0
Provides-Extra: test
Requires-Dist: coverage<=7.13.1,>=7.5.4; extra == 'test'
Requires-Dist: hypothesis<=6.150.2,>=6.104.2; extra == 'test'
Requires-Dist: prek<0.3.0,>=0.2.28; extra == 'test'
Requires-Dist: pylint<=4.0.4,>=3.2.5; extra == 'test'
Requires-Dist: pytest-cov<=7.0.0,>=4.1; extra == 'test'
Requires-Dist: pytest<=9.0.2,>=7.4; extra == 'test'
Requires-Dist: ruff<=0.14.13,>=0.5.0; extra == 'test'
Requires-Dist: ty<=0.0.12,>=0.0.12; extra == 'test'
